alu.v
//======================================================
// Arithmetic Logic Unit (RV32I)
//======================================================
// Performs arithmetic/logical ops based on alu_sel.
//======================================================

module alu (
    input  wire [31:0] a,       // operand A
    input  wire [31:0] b,       // operand B
    input  wire [3:0]  alu_sel, // select from alu_control
    output reg  [31:0] result,
    output wire        zero     // used for branches
);

    // ALU operation encodings (must match alu_control.v)
    localparam ALU_ADD  = 4'b0000;
    localparam ALU_SUB  = 4'b0001;
    localparam ALU_AND  = 4'b0010;
    localparam ALU_OR   = 4'b0011;
    localparam ALU_XOR  = 4'b0100;
    localparam ALU_SLT  = 4'b0101;
    localparam ALU_SLTU = 4'b0110;
    localparam ALU_SLL  = 4'b0111;
    localparam ALU_SRL  = 4'b1000;
    localparam ALU_SRA  = 4'b1001;

    always @(*) begin
        case (alu_sel)
            ALU_ADD  : result = a + b;
            ALU_SUB  : result = a - b;
            ALU_AND  : result = a & b;
            ALU_OR   : result = a | b;
            ALU_XOR  : result = a ^ b;
            ALU_SLT  : result = ($signed(a) < $signed(b)) ? 32'b1 : 32'b0;
            ALU_SLTU : result = (a < b) ? 32'b1 : 32'b0;
            ALU_SLL  : result = a << b[4:0];   // shift amount = lower 5 bits
            ALU_SRL  : result = a >> b[4:0];
            ALU_SRA  : result = $signed(a) >>> b[4:0];
            default  : result = 32'b0;
        endcase
    end

    // Zero flag for branches
    assign zero = (result == 32'b0);

endmodule

tb_alu.v
//======================================================
// Testbench for ALU
//======================================================

`timescale 1ns/1ps
module tb_alu;

    reg  [31:0] a, b;
    reg  [3:0]  alu_sel;
    wire [31:0] result;
    wire        zero;

    // Instantiate ALU
    alu uut (
        .a(a),
        .b(b),
        .alu_sel(alu_sel),
        .result(result),
        .zero(zero)
    );

    initial begin
        $dumpfile("tb_alu.vcd");
        $dumpvars(0, tb_alu);

        // Test ADD
        a = 10; b = 20; alu_sel = 4'b0000; #10;
        $display("ADD: %d + %d = %d", a, b, result);

        // Test SUB
        a = 20; b = 10; alu_sel = 4'b0001; #10;
        $display("SUB: %d - %d = %d", a, b, result);

        // Test AND
        a = 32'hF0F0; b = 32'h0FF0; alu_sel = 4'b0010; #10;
        $display("AND: %h & %h = %h", a, b, result);

        // Test OR
        alu_sel = 4'b0011; #10;
        $display("OR : %h | %h = %h", a, b, result);

        // Test XOR
        alu_sel = 4'b0100; #10;
        $display("XOR: %h ^ %h = %h", a, b, result);

        // Test SLT (signed compare)
        a = -5; b = 3; alu_sel = 4'b0101; #10;
        $display("SLT: %d < %d ? %d", a, b, result);

        // Test SLTU (unsigned compare)
        a = -5; b = 3; alu_sel = 4'b0110; #10;
        $display("SLTU: %u < %u ? %d", a, b, result);

        // Test SLL
        a = 32'h1; b = 32'd4; alu_sel = 4'b0111; #10;
        $display("SLL: %h << %d = %h", a, b, result);

        // Test SRL
        a = 32'hF0; b = 32'd4; alu_sel = 4'b1000; #10;
        $display("SRL: %h >> %d = %h", a, b, result);

        // Test SRA
        a = -32'd16; b = 32'd2; alu_sel = 4'b1001; #10;
        $display("SRA: %d >>> %d = %d", a, b, result);

        // Test Zero flag
        a = 5; b = 5; alu_sel = 4'b0001; #10;
        $display("Zero flag test: %d - %d = %d | zero=%b", a, b, result, zero);

        $finish;
    end

endmodule

tb_alu.vcd
$date
	Tue Sep  2 22:40:15 2025
$end
$version
	Icarus Verilog
$end
$timescale
	1ps
$end
$scope module tb_alu $end
$var wire 1 ! zero $end
$var wire 32 " result [31:0] $end
$var reg 32 # a [31:0] $end
$var reg 4 $ alu_sel [3:0] $end
$var reg 32 % b [31:0] $end
$scope module uut $end
$var wire 32 & a [31:0] $end
$var wire 4 ' alu_sel [3:0] $end
$var wire 32 ( b [31:0] $end
$var wire 1 ! zero $end
$var parameter 4 ) ALU_ADD $end
$var parameter 4 * ALU_AND $end
$var parameter 4 + ALU_OR $end
$var parameter 4 , ALU_SLL $end
$var parameter 4 - ALU_SLT $end
$var parameter 4 . ALU_SLTU $end
$var parameter 4 / ALU_SRA $end
$var parameter 4 0 ALU_SRL $end
$var parameter 4 1 ALU_SUB $end
$var parameter 4 2 ALU_XOR $end
$var reg 32 3 result [31:0] $end
$upscope $end
$upscope $end
$enddefinitions $end
$comment Show the parameter values. $end
$dumpall
b100 2
b1 1
b1000 0
b1001 /
b110 .
b101 -
b111 ,
b11 +
b10 *
b0 )
$end
#0
$dumpvars
b11110 3
b10100 (
b0 '
b1010 &
b10100 %
b0 $
b1010 #
b11110 "
0!
$end
#10000
b1010 "
b1010 3
b1 $
b1 '
b1010 %
b1010 (
b10100 #
b10100 &
#20000
b11110000 "
b11110000 3
b10 $
b10 '
b111111110000 %
b111111110000 (
b1111000011110000 #
b1111000011110000 &
#30000
b1111111111110000 "
b1111111111110000 3
b11 $
b11 '
#40000
b1111111100000000 "
b1111111100000000 3
b100 $
b100 '
#50000
b1 "
b1 3
b101 $
b101 '
b11 %
b11 (
b11111111111111111111111111111011 #
b11111111111111111111111111111011 &
#60000
1!
b0 "
b0 3
b110 $
b110 '
#70000
0!
b10000 "
b10000 3
b111 $
b111 '
b100 %
b100 (
b1 #
b1 &
#80000
b1111 "
b1111 3
b1000 $
b1000 '
b11110000 #
b11110000 &
#90000
b11111111111111111111111111111100 "
b11111111111111111111111111111100 3
b1001 $
b1001 '
b10 %
b10 (
b11111111111111111111111111110000 #
b11111111111111111111111111110000 &
#100000
1!
b0 "
b0 3
b1 $
b1 '
b101 %
b101 (
b101 #
b101 &
