data_mem.v
//======================================================
// Data Memory (for LW/SW)
//======================================================

module data_mem (
    input  wire        clk,
    input  wire        mem_read,
    input  wire        mem_write,
    input  wire [31:0] addr,
    input  wire [31:0] write_data,
    output reg  [31:0] read_data
);

    // 256 x 32-bit memory
    reg [31:0] mem [0:255];

    // Write on rising edge
    always @(posedge clk) begin
        if (mem_write)
            mem[addr[9:2]] <= write_data;
    end

    // Read (combinational)
    always @(*) begin
        if (mem_read)
            read_data = mem[addr[9:2]];
        else
            read_data = 32'b0;
    end

endmodule

alu.v
//======================================================
// Arithmetic Logic Unit (RV32I)
//======================================================
// Performs arithmetic/logical ops based on alu_sel.
//======================================================

module alu (
    input  wire [31:0] a,       // operand A
    input  wire [31:0] b,       // operand B
    input  wire [3:0]  alu_sel, // select from alu_control
    output reg  [31:0] result,
    output wire        zero     // used for branches
);

    // ALU operation encodings (must match alu_control.v)
    localparam ALU_ADD  = 4'b0000;
    localparam ALU_SUB  = 4'b0001;
    localparam ALU_AND  = 4'b0010;
    localparam ALU_OR   = 4'b0011;
    localparam ALU_XOR  = 4'b0100;
    localparam ALU_SLT  = 4'b0101;
    localparam ALU_SLTU = 4'b0110;
    localparam ALU_SLL  = 4'b0111;
    localparam ALU_SRL  = 4'b1000;
    localparam ALU_SRA  = 4'b1001;

    always @(*) begin
        case (alu_sel)
            ALU_ADD  : result = a + b;
            ALU_SUB  : result = a - b;
            ALU_AND  : result = a & b;
            ALU_OR   : result = a | b;
            ALU_XOR  : result = a ^ b;
            ALU_SLT  : result = ($signed(a) < $signed(b)) ? 32'b1 : 32'b0;
            ALU_SLTU : result = (a < b) ? 32'b1 : 32'b0;
            ALU_SLL  : result = a << b[4:0];   // shift amount = lower 5 bits
            ALU_SRL  : result = a >> b[4:0];
            ALU_SRA  : result = $signed(a) >>> b[4:0];
            default  : result = 32'b0;
        endcase
    end

    // Zero flag for branches
    assign zero = (result == 32'b0);

endmodule

alu_control.v
//======================================================
// ALU Control (RV32I)
//======================================================
module alu_control (
    input  wire [1:0] alu_op,
    input  wire [2:0] funct3,    // instr[14:12]
    input  wire       funct7b5,  // instr[30]
    output reg  [3:0] alu_sel
);

    // ALU operation encodings
    localparam ALU_ADD  = 4'b0000;
    localparam ALU_SUB  = 4'b0001;
    localparam ALU_AND  = 4'b0010;
    localparam ALU_OR   = 4'b0011;
    localparam ALU_XOR  = 4'b0100;
    localparam ALU_SLT  = 4'b0101;
    localparam ALU_SLTU = 4'b0110;
    localparam ALU_SLL  = 4'b0111;
    localparam ALU_SRL  = 4'b1000;
    localparam ALU_SRA  = 4'b1001;

    always @* begin
        case (alu_op)
            2'b00: alu_sel = ALU_ADD; // loads/stores/AUIPC
            2'b01: alu_sel = ALU_SUB; // branches
            2'b10: begin
                case (funct3)
                    3'b000: alu_sel = (funct7b5 ? ALU_SUB : ALU_ADD);
                    3'b111: alu_sel = ALU_AND;
                    3'b110: alu_sel = ALU_OR;
                    3'b100: alu_sel = ALU_XOR;
                    3'b010: alu_sel = ALU_SLT;
                    3'b011: alu_sel = ALU_SLTU;
                    3'b001: alu_sel = ALU_SLL;
                    3'b101: alu_sel = (funct7b5 ? ALU_SRA : ALU_SRL);
                    default: alu_sel = ALU_ADD;
                endcase
            end
            default: alu_sel = ALU_ADD;
        endcase
    end
endmodule

regfile.v
//======================================================
// Register File (32 x 32-bit)
//======================================================

module regfile (
    input  wire        clk,
    input  wire        we,           // write enable
    input  wire [4:0]  rs1,          // source register 1
    input  wire [4:0]  rs2,          // source register 2
    input  wire [4:0]  rd,           // destination register
    input  wire [31:0] wd,           // write data
    output wire [31:0] rd1,          // read data 1
    output wire [31:0] rd2           // read data 2
);

    reg [31:0] regs [0:31];

    // Read is asynchronous
    assign rd1 = (rs1 != 0) ? regs[rs1] : 0;  // x0 always 0
    assign rd2 = (rs2 != 0) ? regs[rs2] : 0;

    // Write is synchronous
    always @(posedge clk) begin
        if (we && (rd != 0))  // cannot write to x0
            regs[rd] <= wd;
    end

endmodule

imm_gen.v
//======================================================
// Immediate Generator (RISC-V)
//======================================================
// Supports: I-type, S-type, B-type, U-type, J-type
//======================================================

module imm_gen (
    input  wire [31:0] instr,     // full instruction
    output reg  [31:0] imm_out    // sign-extended immediate
);

    wire [6:0] opcode;
    assign opcode = instr[6:0];

    always @(*) begin
        case (opcode)
            // I-type (ADDI, LW, JALR, etc.)
            7'b0010011, // ADDI
            7'b0000011, // LW
            7'b1100111: // JALR
                imm_out = {{20{instr[31]}}, instr[31:20]};

            // S-type (SW)
            7'b0100011:
                imm_out = {{20{instr[31]}}, instr[31:25], instr[11:7]};

            // B-type (BEQ, BNE, etc.)
            7'b1100011:
                imm_out = {{19{instr[31]}}, instr[31], instr[7],
                           instr[30:25], instr[11:8], 1'b0};

            // U-type (LUI, AUIPC)
            7'b0110111, // LUI
            7'b0010111: // AUIPC
                imm_out = {instr[31:12], 12'b0};

            // J-type (JAL)
            7'b1101111:
                imm_out = {{11{instr[31]}}, instr[31],
                           instr[19:12], instr[20],
                           instr[30:21], 1'b0};

            // Default (R-type, NOP, etc.)
            default:
                imm_out = 32'b0;
        endcase
    end

endmodule

control.v
//======================================================
// Main Control Unit (RV32I)
//======================================================
// Decodes opcode into high-level control signals.
// - Uses ALUOp for secondary decode in alu_control.
// - mem_to_reg: 1 -> write back from memory (loads)
// - alu_src   : 1 -> ALU B comes from immediate
// - branch    : 1 -> branch instruction (uses ALU for compare)
// - jump      : 1 -> JAL/JALR (write rd=PC+4; PC update via next-PC logic)
// - lui       : 1 -> write rd = imm (top-level will mux this later)
// - auipc     : 1 -> write rd = PC + imm (top-level will use PC as ALU srcA)
module control (
    input  wire [6:0] opcode,       // instr[6:0]
    output reg        reg_write,
    output reg        mem_read,
    output reg        mem_write,
    output reg        mem_to_reg,
    output reg        alu_src,
    output reg        branch,
    output reg        jump,
    output reg        lui,
    output reg        auipc,
    output reg [1:0]  alu_op        // 00: ADD, 01: BRANCH(SUB), 10: R/I decode
);

    always @* begin
        // Safe defaults
        reg_write = 0;
        mem_read  = 0;
        mem_write = 0;
        mem_to_reg= 0;
        alu_src   = 0;
        branch    = 0;
        jump      = 0;
        lui       = 0;
        auipc     = 0;
        alu_op    = 2'b00;

        case (opcode)
            7'b0110011: begin // R-type (ADD,SUB,AND,OR,XOR,SLL,SRL,SRA,SLT,SLTU)
                reg_write = 1;
                alu_src   = 0;
                alu_op    = 2'b10;
            end

            7'b0010011: begin // I-type ALU (ADDI, ANDI, ORI, XORI, SLLI, SRLI, SRAI, SLTI, SLTIU)
                reg_write = 1;
                alu_src   = 1;
                alu_op    = 2'b10;
            end

            7'b0000011: begin // LOAD (e.g., LW)
                reg_write = 1;
                mem_read  = 1;
                mem_to_reg= 1;
                alu_src   = 1;    // addr = rs1 + imm
                alu_op    = 2'b00; // ADD
            end

            7'b0100011: begin // STORE (e.g., SW)
                mem_write = 1;
                alu_src   = 1;    // addr = rs1 + imm
                alu_op    = 2'b00; // ADD
            end

            7'b1100011: begin // BRANCH (BEQ/BNE/BLT/...)
                branch    = 1;
                alu_src   = 0;
                alu_op    = 2'b01; // use SUB/compare in ALU
            end

            7'b1101111: begin // JAL
                reg_write = 1;    // rd = PC+4 (top will mux)
                jump      = 1;
                // alu_op don't care
            end

            7'b1100111: begin // JALR
                reg_write = 1;    // rd = PC+4
                jump      = 1;
                alu_src   = 1;    // target = rs1 + imm (handled in next PC logic)
                // alu_op don't care
            end

            7'b0110111: begin // LUI
                reg_write = 1;
                lui       = 1;    // rd = imm (top-level mux)
            end

            7'b0010111: begin // AUIPC
                reg_write = 1;
                auipc     = 1;    // rd = PC + imm (top uses PC as ALU srcA)
                alu_op    = 2'b00; // ADD
            end

            7'b1110011: begin // SYSTEM (e.g., ECALL) -> no writes in our simple core
                // all defaults
            end
        endcase
    end
endmodule

instr_mem.v
//======================================================
// Instruction Memory (Read-Only)
//======================================================

module instr_mem (
    input  wire [31:0] addr,       // PC address
    output wire [31:0] instr       // Instruction at addr
);

    // 256 x 32-bit memory (can hold 256 instructions)
    reg [31:0] mem [0:255];

    initial begin
        //==================================================
        // Test Program: JAL + JALR with clean return
        // x1 = 5
        // JAL to func: save PC+4 into x5 (link register)
        // func: x2 = x1 + 7
        // JALR back using x5
        // program halts with ECALL
        //==================================================

        mem[0] = 32'h00500093; // ADDI x1, x0, 5
        mem[1] = 32'h008002ef; // JAL x5, +8 (jump to PC=0x0C, x5=PC+4=0x08)
        mem[2] = 32'h00000073; // ECALL (halt after return)

        // function body @ PC=0x0C
        mem[3] = 32'h00708113; // ADDI x2, x1, 7  ; x2 = 12
        mem[4] = 32'h00028067; // JALR x0, 0(x5)  ; return to address in x5
    end

    // Word aligned access: addr[31:2]
    assign instr = mem[addr[9:2]];

endmodule

pc.v
//======================================================
// Program Counter (PC)
//======================================================

module pc (
    input  wire        clk,
    input  wire        reset,
    input  wire [31:0] next_pc,   // next PC value (from PC logic)
    output reg  [31:0] pc_out     // current PC value
);

    always @(posedge clk or posedge reset) begin
        if (reset)
            pc_out <= 32'h00000000;   // start at address 0
        else
            pc_out <= next_pc;        // update with next PC
    end

endmodule

cpu_top.v
//======================================================
// Top-Level CPU (Single-Cycle RV32I Core)
//======================================================

module cpu_top (
    input  wire clk,
    input  wire reset,

    // Debug outputs for testbench visibility
    output wire [31:0] alu_result,
    output wire        alu_zero,
    output wire        branch,
    output wire [31:0] imm_out
);

    // --- PC & Instruction Memory ---
    wire [31:0] pc_out, next_pc, instr;

    pc pc_inst (
        .clk(clk),
        .reset(reset),
        .next_pc(next_pc),
        .pc_out(pc_out)
    );

    instr_mem imem_inst (
        .addr(pc_out),
        .instr(instr)
    );

    // --- Decode Fields ---
    wire [6:0] opcode  = instr[6:0];
    wire [4:0] rd      = instr[11:7];
    wire [2:0] funct3  = instr[14:12];
    wire [4:0] rs1     = instr[19:15];
    wire [4:0] rs2     = instr[24:20];
    wire [6:0] funct7  = instr[31:25];

    // --- Control Signals ---
    wire reg_write, mem_read, mem_write, mem_to_reg;
    wire alu_src, jump, lui, auipc;
    wire [1:0] alu_op;

    control control_inst (
        .opcode(opcode),
        .reg_write(reg_write),
        .mem_read(mem_read),
        .mem_write(mem_write),
        .mem_to_reg(mem_to_reg),
        .alu_src(alu_src),
        .branch(branch),   // exposed
        .jump(jump),
        .lui(lui),
        .auipc(auipc),
        .alu_op(alu_op)
    );

    // --- Immediate Generator ---
    imm_gen imm_inst (
        .instr(instr),
        .imm_out(imm_out)  // exposed
    );

    // --- Register File ---
    wire [31:0] rd1, rd2;
    wire [31:0] write_data;

    regfile rf_inst (
        .clk(clk),
        .we(reg_write),
        .rs1(rs1),
        .rs2(rs2),
        .rd(rd),
        .wd(write_data),
        .rd1(rd1),
        .rd2(rd2)
    );

    // --- ALU Control ---
    wire [3:0] alu_sel;
    alu_control alu_ctrl_inst (
        .alu_op(alu_op),
        .funct3(funct3),
        .funct7b5(funct7[5]),
        .alu_sel(alu_sel)
    );

    // --- ALU ---
    wire [31:0] alu_b = (alu_src) ? imm_out : rd2;

    alu alu_inst (
        .a(rd1),
        .b(alu_b),
        .alu_sel(alu_sel),
        .result(alu_result), // exposed
        .zero(alu_zero)      // exposed
    );

    // --- Data Memory ---
    wire [31:0] data_read;

    data_mem dmem_inst (
        .clk(clk),
        .mem_read(mem_read),
        .mem_write(mem_write),
        .addr(alu_result),
        .write_data(rd2),
        .read_data(data_read)
    );

    // --- Write-back Selection ---
    assign write_data =
        (lui)   ? imm_out :
        (auipc) ? (pc_out + imm_out) :
        (jump)  ? (pc_out + 4) :             // FIX: JAL/JALR write PC+4 into rd
        (mem_to_reg ? data_read : alu_result);

    // --- Next PC Logic with Branch/Jump ---
    wire take_branch   = branch & alu_zero;
    wire [31:0] pc_plus_4 = pc_out + 4;
    wire [31:0] pc_branch = pc_out + imm_out;
    wire [31:0] pc_jalr   = (rd1 + imm_out) & ~32'b1; // JALR target, LSB forced 0

    assign next_pc = jump ? (opcode == 7'b1101111 ? pc_out + imm_out : pc_jalr) :
                      take_branch ? pc_branch :
                      pc_plus_4;

endmodule

tb_cpu.v
//======================================================
// Testbench for CPU Top (Single-Cycle RV32I)
//======================================================

`timescale 1ns/1ps
module tb_cpu;

    reg clk, reset;

    // Instantiate CPU with debug outputs
    wire [31:0] alu_result;
    wire        alu_zero;
    wire        branch;
    wire [31:0] imm_out;

    cpu_top uut (
        .clk(clk),
        .reset(reset),
        .alu_result(alu_result),
        .alu_zero(alu_zero),
        .branch(branch),
        .imm_out(imm_out)
    );

    // Clock generator: 10 ns period
    always #5 clk = ~clk;

    initial begin
        $dumpfile("tb_cpu.vcd");
        $dumpvars(0, tb_cpu);

        // Init
        clk = 0;
        reset = 1;
        #10 reset = 0;

        // Run for a while
        #100 $finish;
    end

    // Monitor PC + key registers + debug signals
    initial begin
        $monitor("T=%0t | PC=%h | x1=%d x2=%d x3=%d x4=%d x5=%h | alu_res=%d zero=%b branch=%b imm=%d",
                  $time,
                  uut.pc_out,
                  uut.rf_inst.regs[1],
                  uut.rf_inst.regs[2],
                  uut.rf_inst.regs[3],
                  uut.rf_inst.regs[4],
                  uut.rf_inst.regs[5],  // monitor x5 (link register)
                  alu_result,
                  alu_zero,
                  branch,
                  imm_out);
    end

endmodule

tb_cpu.vcd
$date
	Tue Sep  2 23:16:26 2025
$end
$version
	Icarus Verilog
$end
$timescale
	1ps
$end
$scope module tb_cpu $end
$var wire 32 ! imm_out [31:0] $end
$var wire 1 " branch $end
$var wire 1 # alu_zero $end
$var wire 32 $ alu_result [31:0] $end
$var reg 1 % clk $end
$var reg 1 & reset $end
$scope module uut $end
$var wire 1 % clk $end
$var wire 32 ' pc_jalr [31:0] $end
$var wire 1 & reset $end
$var wire 1 ( take_branch $end
$var wire 32 ) write_data [31:0] $end
$var wire 5 * rs2 [4:0] $end
$var wire 5 + rs1 [4:0] $end
$var wire 1 , reg_write $end
$var wire 32 - rd2 [31:0] $end
$var wire 32 . rd1 [31:0] $end
$var wire 5 / rd [4:0] $end
$var wire 32 0 pc_plus_4 [31:0] $end
$var wire 32 1 pc_out [31:0] $end
$var wire 32 2 pc_branch [31:0] $end
$var wire 7 3 opcode [6:0] $end
$var wire 32 4 next_pc [31:0] $end
$var wire 1 5 mem_write $end
$var wire 1 6 mem_to_reg $end
$var wire 1 7 mem_read $end
$var wire 1 8 lui $end
$var wire 1 9 jump $end
$var wire 32 : instr [31:0] $end
$var wire 32 ; imm_out [31:0] $end
$var wire 7 < funct7 [6:0] $end
$var wire 3 = funct3 [2:0] $end
$var wire 32 > data_read [31:0] $end
$var wire 1 " branch $end
$var wire 1 ? auipc $end
$var wire 1 # alu_zero $end
$var wire 1 @ alu_src $end
$var wire 4 A alu_sel [3:0] $end
$var wire 32 B alu_result [31:0] $end
$var wire 2 C alu_op [1:0] $end
$var wire 32 D alu_b [31:0] $end
$scope module alu_ctrl_inst $end
$var wire 3 E funct3 [2:0] $end
$var wire 1 F funct7b5 $end
$var wire 2 G alu_op [1:0] $end
$var parameter 4 H ALU_ADD $end
$var parameter 4 I ALU_AND $end
$var parameter 4 J ALU_OR $end
$var parameter 4 K ALU_SLL $end
$var parameter 4 L ALU_SLT $end
$var parameter 4 M ALU_SLTU $end
$var parameter 4 N ALU_SRA $end
$var parameter 4 O ALU_SRL $end
$var parameter 4 P ALU_SUB $end
$var parameter 4 Q ALU_XOR $end
$var reg 4 R alu_sel [3:0] $end
$upscope $end
$scope module alu_inst $end
$var wire 4 S alu_sel [3:0] $end
$var wire 32 T b [31:0] $end
$var wire 1 # zero $end
$var wire 32 U a [31:0] $end
$var parameter 4 V ALU_ADD $end
$var parameter 4 W ALU_AND $end
$var parameter 4 X ALU_OR $end
$var parameter 4 Y ALU_SLL $end
$var parameter 4 Z ALU_SLT $end
$var parameter 4 [ ALU_SLTU $end
$var parameter 4 \ ALU_SRA $end
$var parameter 4 ] ALU_SRL $end
$var parameter 4 ^ ALU_SUB $end
$var parameter 4 _ ALU_XOR $end
$var reg 32 ` result [31:0] $end
$upscope $end
$scope module control_inst $end
$var wire 7 a opcode [6:0] $end
$var reg 2 b alu_op [1:0] $end
$var reg 1 @ alu_src $end
$var reg 1 ? auipc $end
$var reg 1 " branch $end
$var reg 1 9 jump $end
$var reg 1 8 lui $end
$var reg 1 7 mem_read $end
$var reg 1 6 mem_to_reg $end
$var reg 1 5 mem_write $end
$var reg 1 , reg_write $end
$upscope $end
$scope module dmem_inst $end
$var wire 32 c addr [31:0] $end
$var wire 1 % clk $end
$var wire 1 7 mem_read $end
$var wire 1 5 mem_write $end
$var wire 32 d write_data [31:0] $end
$var reg 32 e read_data [31:0] $end
$upscope $end
$scope module imem_inst $end
$var wire 32 f instr [31:0] $end
$var wire 32 g addr [31:0] $end
$upscope $end
$scope module imm_inst $end
$var wire 32 h instr [31:0] $end
$var wire 7 i opcode [6:0] $end
$var reg 32 j imm_out [31:0] $end
$upscope $end
$scope module pc_inst $end
$var wire 1 % clk $end
$var wire 32 k next_pc [31:0] $end
$var wire 1 & reset $end
$var reg 32 l pc_out [31:0] $end
$upscope $end
$scope module rf_inst $end
$var wire 1 % clk $end
$var wire 5 m rd [4:0] $end
$var wire 5 n rs1 [4:0] $end
$var wire 5 o rs2 [4:0] $end
$var wire 32 p wd [31:0] $end
$var wire 1 , we $end
$var wire 32 q rd2 [31:0] $end
$var wire 32 r rd1 [31:0] $end
$upscope $end
$upscope $end
$upscope $end
$enddefinitions $end
$comment Show the parameter values. $end
$dumpall
b100 _
b1 ^
b1000 ]
b1001 \
b110 [
b101 Z
b111 Y
b11 X
b10 W
b0 V
b100 Q
b1 P
b1000 O
b1001 N
b110 M
b101 L
b111 K
b11 J
b10 I
b0 H
$end
#0
$dumpvars
b0 r
bx q
b101 p
b101 o
b0 n
b1 m
b0 l
b100 k
b101 j
b10011 i
b10100000000000010010011 h
b0 g
b10100000000000010010011 f
b0 e
bx d
b101 c
b10 b
b10011 a
b101 `
b0 U
b101 T
b0 S
b0 R
b10 G
0F
b0 E
b101 D
b10 C
b101 B
b0 A
1@
0?
b0 >
b0 =
b0 <
b101 ;
b10100000000000010010011 :
09
08
07
06
05
b100 4
b10011 3
b101 2
b0 1
b100 0
b1 /
b0 .
bx -
1,
b0 +
b101 *
b101 )
0(
b100 '
1&
0%
b101 $
0#
0"
b101 !
$end
#5000
1%
#10000
0%
0&
#15000
b1000 )
b1000 p
x#
bx $
bx B
bx `
bx c
b1000 '
bx D
bx T
19
b0 C
b0 G
b0 b
0@
1,
b1000 !
b1000 ;
b1000 j
b1101111 i
b1000 *
b1000 o
b101 /
b101 m
b1101111 3
b1101111 a
b1100 4
b1100 k
b100000000000001011101111 :
b100000000000001011101111 f
b100000000000001011101111 h
b1100 2
b1000 0
b100 1
b100 g
b100 l
1%
#20000
0%
#25000
0#
b1100 $
b1100 B
b1100 `
b1100 c
b111 D
b111 T
b1100 '
b101 .
b101 U
b101 r
b10 C
b10 G
b10 b
1@
09
1,
b1100 )
b1100 p
b111 !
b111 ;
b111 j
b10011 i
b111 *
b111 o
b1 +
b1 n
b10 /
b10 m
b10011 3
b10011 a
b10000 4
b10000 k
b11100001000000100010011 :
b11100001000000100010011 f
b11100001000000100010011 h
b10011 2
b10000 0
b1100 1
b1100 g
b1100 l
1%
#30000
0%
#35000
b10100 )
b10100 p
b1000 $
b1000 B
b1000 `
b1000 c
b1000 '
b0 D
b0 T
b0 -
b0 d
b0 q
b1000 .
b1000 U
b1000 r
19
b0 C
b0 G
b0 b
1@
1,
b0 !
b0 ;
b0 j
b1100111 i
b0 *
b0 o
b101 +
b101 n
b0 /
b0 m
b1100111 3
b1100111 a
b1000 4
b1000 k
b101000000001100111 :
b101000000001100111 f
b101000000001100111 h
b10000 2
b10100 0
b10000 1
b10000 g
b10000 l
1%
#40000
0%
#45000
b0 '
1#
b0 $
b0 B
b0 `
b0 c
b1100 4
b1100 k
b0 .
b0 U
b0 r
09
0@
0,
b0 )
b0 p
b1110011 i
b0 +
b0 n
b1110011 3
b1110011 a
b1110011 :
b1110011 f
b1110011 h
b1000 2
b1100 0
b1000 1
b1000 g
b1000 l
1%
#50000
0%
#55000
b1100 )
b1100 p
0#
b1100 $
b1100 B
b1100 `
b1100 c
b111 D
b111 T
b1100 '
bx -
bx d
bx q
b101 .
b101 U
b101 r
b10 C
b10 G
b10 b
1@
1,
b111 !
b111 ;
b111 j
b10011 i
b111 *
b111 o
b1 +
b1 n
b10 /
b10 m
b10011 3
b10011 a
b10000 4
b10000 k
b11100001000000100010011 :
b11100001000000100010011 f
b11100001000000100010011 h
b10011 2
b10000 0
b1100 1
b1100 g
b1100 l
1%
#60000
0%
#65000
b10100 )
b10100 p
b1000 $
b1000 B
b1000 `
b1000 c
b1000 '
b0 D
b0 T
b0 -
b0 d
b0 q
b1000 .
b1000 U
b1000 r
19
b0 C
b0 G
b0 b
1@
1,
b0 !
b0 ;
b0 j
b1100111 i
b0 *
b0 o
b101 +
b101 n
b0 /
b0 m
b1100111 3
b1100111 a
b1000 4
b1000 k
b101000000001100111 :
b101000000001100111 f
b101000000001100111 h
b10000 2
b10100 0
b10000 1
b10000 g
b10000 l
1%
#70000
0%
#75000
b0 '
1#
b0 $
b0 B
b0 `
b0 c
b1100 4
b1100 k
b0 .
b0 U
b0 r
09
0@
0,
b0 )
b0 p
b1110011 i
b0 +
b0 n
b1110011 3
b1110011 a
b1110011 :
b1110011 f
b1110011 h
b1000 2
b1100 0
b1000 1
b1000 g
b1000 l
1%
#80000
0%
#85000
b1100 )
b1100 p
0#
b1100 $
b1100 B
b1100 `
b1100 c
b111 D
b111 T
b1100 '
bx -
bx d
bx q
b101 .
b101 U
b101 r
b10 C
b10 G
b10 b
1@
1,
b111 !
b111 ;
b111 j
b10011 i
b111 *
b111 o
b1 +
b1 n
b10 /
b10 m
b10011 3
b10011 a
b10000 4
b10000 k
b11100001000000100010011 :
b11100001000000100010011 f
b11100001000000100010011 h
b10011 2
b10000 0
b1100 1
b1100 g
b1100 l
1%
#90000
0%
#95000
b10100 )
b10100 p
b1000 $
b1000 B
b1000 `
b1000 c
b1000 '
b0 D
b0 T
b0 -
b0 d
b0 q
b1000 .
b1000 U
b1000 r
19
b0 C
b0 G
b0 b
1@
1,
b0 !
b0 ;
b0 j
b1100111 i
b0 *
b0 o
b101 +
b101 n
b0 /
b0 m
b1100111 3
b1100111 a
b1000 4
b1000 k
b101000000001100111 :
b101000000001100111 f
b101000000001100111 h
b10000 2
b10100 0
b10000 1
b10000 g
b10000 l
1%
#100000
0%
#105000
b0 '
1#
b0 $
b0 B
b0 `
b0 c
b1100 4
b1100 k
b0 .
b0 U
b0 r
09
0@
0,
b0 )
b0 p
b1110011 i
b0 +
b0 n
b1110011 3
b1110011 a
b1110011 :
b1110011 f
b1110011 h
b1000 2
b1100 0
b1000 1
b1000 g
b1000 l
1%
