pc.v
//======================================================
// Program Counter (PC)
//======================================================

module pc (
    input  wire        clk,
    input  wire        reset,
    input  wire [31:0] next_pc,   // next PC value (from PC logic)
    output reg  [31:0] pc_out     // current PC value
);

    always @(posedge clk or posedge reset) begin
        if (reset)
            pc_out <= 32'h00000000;   // start at address 0
        else
            pc_out <= next_pc;        // update with next PC
    end

endmodule

tb_pc.v
//======================================================
// Testbench for Program Counter (PC)
//======================================================

`timescale 1ns/1ps
module tb_pc;

    reg clk;
    reg reset;
    reg [31:0] next_pc;
    wire [31:0] pc_out;

    // Instantiate PC
    pc uut (
        .clk(clk),
        .reset(reset),
        .next_pc(next_pc),
        .pc_out(pc_out)
    );

    // Clock generator (10ns period)
    always #5 clk = ~clk;

    initial begin
        $dumpfile("tb_pc.vcd");   // for GTKWave
        $dumpvars(0, tb_pc);

        // Init
        clk = 0; reset = 1; next_pc = 0;
        #10 reset = 0;

        // Step through PC values
        next_pc = 32'h00000004; #10;
        next_pc = 32'h00000008; #10;
        next_pc = 32'h0000000C; #10;
        next_pc = 32'h00000010; #10;

        $finish;
    end

endmodule

tb_pc.vcd
$date
	Tue Sep  2 22:15:02 2025
$end
$version
	Icarus Verilog
$end
$timescale
	1ps
$end
$scope module tb_pc $end
$var wire 32 ! pc_out [31:0] $end
$var reg 1 " clk $end
$var reg 32 # next_pc [31:0] $end
$var reg 1 $ reset $end
$scope module uut $end
$var wire 1 " clk $end
$var wire 32 % next_pc [31:0] $end
$var wire 1 $ reset $end
$var reg 32 & pc_out [31:0] $end
$upscope $end
$upscope $end
$enddefinitions $end
$comment Show the parameter values. $end
$dumpall
$end
#0
$dumpvars
b0 &
b0 %
1$
b0 #
0"
b0 !
$end
#5000
1"
#10000
0"
b100 #
b100 %
0$
#15000
b100 !
b100 &
1"
#20000
0"
b1000 #
b1000 %
#25000
b1000 !
b1000 &
1"
#30000
0"
b1100 #
b1100 %
#35000
b1100 !
b1100 &
1"
#40000
0"
b10000 #
b10000 %
#45000
b10000 !
b10000 &
1"
