regfile.v
//======================================================
// Register File (32 x 32-bit)
//======================================================

module regfile (
    input  wire        clk,
    input  wire        we,           // write enable
    input  wire [4:0]  rs1,          // source register 1
    input  wire [4:0]  rs2,          // source register 2
    input  wire [4:0]  rd,           // destination register
    input  wire [31:0] wd,           // write data
    output wire [31:0] rd1,          // read data 1
    output wire [31:0] rd2           // read data 2
);

    reg [31:0] regs [0:31];

    // Read is asynchronous
    assign rd1 = (rs1 != 0) ? regs[rs1] : 0;  // x0 always 0
    assign rd2 = (rs2 != 0) ? regs[rs2] : 0;

    // Write is synchronous
    always @(posedge clk) begin
        if (we && (rd != 0))  // cannot write to x0
            regs[rd] <= wd;
    end

endmodule

tb_regfile.v
//======================================================
// Testbench for Register File
//======================================================

`timescale 1ns/1ps
module tb_regfile;

    reg clk;
    reg we;
    reg [4:0] rs1, rs2, rd;
    reg [31:0] wd;
    wire [31:0] rd1, rd2;

    // Instantiate regfile
    regfile uut (
        .clk(clk),
        .we(we),
        .rs1(rs1),
        .rs2(rs2),
        .rd(rd),
        .wd(wd),
        .rd1(rd1),
        .rd2(rd2)
    );

    // Clock generator
    always #5 clk = ~clk;

    initial begin
        $dumpfile("tb_regfile.vcd");
        $dumpvars(0, tb_regfile);

        // Init
        clk = 0; we = 0; rs1 = 0; rs2 = 0; rd = 0; wd = 0;

        // Write 10 into x1
        #10 we = 1; rd = 5'd1; wd = 32'd10;
        #10 we = 0;

        // Write 20 into x2
        #10 we = 1; rd = 5'd2; wd = 32'd20;
        #10 we = 0;

        // Read from x1 and x2
        #10 rs1 = 5'd1; rs2 = 5'd2;

        // Try to write to x0 (should stay 0)
        #10 we = 1; rd = 5'd0; wd = 32'd99;
        #10 we = 0;

        // Read x0
        #10 rs1 = 5'd0; rs2 = 5'd0;

        #20 $finish;
    end

    // Monitor
    initial begin
        $monitor("T=%0t | rs1=%d rd1=%d | rs2=%d rd2=%d", 
                  $time, rs1, rd1, rs2, rd2);
    end

endmodule

tb_regfile.vcd
$date
	Tue Sep  2 22:30:57 2025
$end
$version
	Icarus Verilog
$end
$timescale
	1ps
$end
$scope module tb_regfile $end
$var wire 32 ! rd2 [31:0] $end
$var wire 32 " rd1 [31:0] $end
$var reg 1 # clk $end
$var reg 5 $ rd [4:0] $end
$var reg 5 % rs1 [4:0] $end
$var reg 5 & rs2 [4:0] $end
$var reg 32 ' wd [31:0] $end
$var reg 1 ( we $end
$scope module uut $end
$var wire 1 # clk $end
$var wire 5 ) rd [4:0] $end
$var wire 5 * rs1 [4:0] $end
$var wire 5 + rs2 [4:0] $end
$var wire 32 , wd [31:0] $end
$var wire 1 ( we $end
$var wire 32 - rd2 [31:0] $end
$var wire 32 . rd1 [31:0] $end
$upscope $end
$upscope $end
$enddefinitions $end
$comment Show the parameter values. $end
$dumpall
$end
#0
$dumpvars
b0 .
b0 -
b0 ,
b0 +
b0 *
b0 )
0(
b0 '
b0 &
b0 %
b0 $
0#
b0 "
b0 !
$end
#5000
1#
#10000
0#
b1010 '
b1010 ,
b1 $
b1 )
1(
#15000
1#
#20000
0#
0(
#25000
1#
#30000
0#
b10100 '
b10100 ,
b10 $
b10 )
1(
#35000
1#
#40000
0#
0(
#45000
1#
#50000
b10100 !
b10100 -
b1010 "
b1010 .
0#
b10 &
b10 +
b1 %
b1 *
#55000
1#
#60000
0#
b1100011 '
b1100011 ,
b0 $
b0 )
1(
#65000
1#
#70000
0#
0(
#75000
1#
#80000
b0 !
b0 -
b0 "
b0 .
0#
b0 &
b0 +
b0 %
b0 *
